MANIFEST.in
README.md
setup.py
pyplate/__init__.py
pyplate/_version.py
pyplate/conf.py
pyplate/image.py
pyplate/metadata.py
pyplate.egg-info/PKG-INFO
pyplate.egg-info/SOURCES.txt
pyplate.egg-info/dependency_links.txt
pyplate.egg-info/requires.txt
pyplate.egg-info/top_level.txt
pyplate/database/__init__.py
pyplate/database/applause_dr4.yaml
pyplate/database/database.py
pyplate/database/db_mysql.py
pyplate/database/db_pgsql.py
pyplate/database/db_yaml.py
pyplate/process/__init__.py
pyplate/process/artifact_model.h5
pyplate/process/astrometry.py
pyplate/process/catalog.py
pyplate/process/photometry.py
pyplate/process/pipeline.py
pyplate/process/process.py
pyplate/process/solve.py
pyplate/process/sources.py