Metadata-Version: 2.1
Name: pyplate
Version: 4.0.11
Summary: A Python package for processing astronomical photographic plates
Home-page: https://github.com/astrotuvi/pyplate
Author: Taavi Tuvikene
Author-email: taavi.tuvikene@ut.ee
License: Apache License, Version 2.0
Platform: UNKNOWN
Classifier: Programming Language :: Python
Classifier: Programming Language :: Python :: 3
Classifier: Development Status :: 5 - Production/Stable
Classifier: Intended Audience :: Science/Research
Classifier: License :: OSI Approved :: Apache Software License
Classifier: Topic :: Scientific/Engineering :: Astronomy
Provides-Extra: ml
Provides-Extra: pgsql
Provides-Extra: mysql
